MANIFEST.in
README.rst
setup.py
IPS_Vagrant.egg-info/PKG-INFO
IPS_Vagrant.egg-info/SOURCES.txt
IPS_Vagrant.egg-info/dependency_links.txt
IPS_Vagrant.egg-info/entry_points.txt
IPS_Vagrant.egg-info/requires.txt
IPS_Vagrant.egg-info/top_level.txt
ips_vagrant/WELCOME.rst
ips_vagrant/__init__.py
ips_vagrant/alembic.ini
ips_vagrant/cli.py
ips_vagrant/commands/__init__.py
ips_vagrant/commands/delete/__init__.py
ips_vagrant/commands/disable/__init__.py
ips_vagrant/commands/enable/__init__.py
ips_vagrant/commands/list/__init__.py
ips_vagrant/commands/mysql/__init__.py
ips_vagrant/commands/new/__init__.py
ips_vagrant/commands/setup/__init__.py
ips_vagrant/commands/versions/__init__.py
ips_vagrant/common/__init__.py
ips_vagrant/common/progress.py
ips_vagrant/common/ssl.py
ips_vagrant/common/version.py
ips_vagrant/config/ipsv.conf
ips_vagrant/downloaders/__init__.py
ips_vagrant/downloaders/dev_tools.py
ips_vagrant/downloaders/downloader.py
ips_vagrant/downloaders/ips.py
ips_vagrant/generators/__init__.py
ips_vagrant/generators/generator.py
ips_vagrant/generators/nginx.py
ips_vagrant/generators/php5_fpm.py
ips_vagrant/generators/templates/nginx/server.tpl
ips_vagrant/generators/templates/php5-fpm/pool.tpl
ips_vagrant/installer/V_4_0_11.py
ips_vagrant/installer/V_4_1_3_2.py
ips_vagrant/installer/__init__.py
ips_vagrant/installer/latest.py
ips_vagrant/installer/dev_tools/__init__.py
ips_vagrant/installer/dev_tools/latest.py
ips_vagrant/man/ipsv.1
ips_vagrant/man/overview.rst
ips_vagrant/migrations/__init__.py
ips_vagrant/migrations/env.py
ips_vagrant/migrations/versions/2015_09_18_3a94451d9c60_initial_setup.py
ips_vagrant/migrations/versions/__init__.py
ips_vagrant/models/__init__.py
ips_vagrant/models/sites.py
ips_vagrant/scrapers/__init__.py
ips_vagrant/scrapers/errors.py
ips_vagrant/scrapers/licenses.py
ips_vagrant/scrapers/login.py