Metadata-Version: 1.1
Name: IPS-Vagrant
Version: 0.4.1
Summary: A management utility for the (unofficial) Invision Power Suite Vagrant development box.
Home-page: https://github.com/FujiMakoto/IPS-Vagrant
Author: Makoto Fujimoto
Author-email: makoto@makoto.io
License: MIT
Platform: UNKNOWN
Classifier: Development Status :: 3 - Alpha
Classifier: License :: OSI Approved :: MIT License
Classifier: Environment :: Console
Classifier: Intended Audience :: Developers
Classifier: Operating System :: POSIX :: Linux
Classifier: Programming Language :: PHP
Classifier: Topic :: Software Development
Classifier: Topic :: Software Development :: Code Generators
Classifier: Topic :: System :: Installation/Setup
Classifier: Topic :: System :: Systems Administration
Classifier: Topic :: Utilities
